[
    {
        "key": "sb",
        "value": "tCfiZC5Jfqcvq-I4BTi7BAQI",
        "domain": "facebook.com",
        "path": "/",
        "hostOnly": false,
        "creation": "2024-12-25T04:58:11.034Z",
        "lastAccessed": "2024-12-25T04:58:11.034Z"
    },
    {
        "key": "ps_n",
        "value": "1",
        "domain": "facebook.com",
        "path": "/",
        "hostOnly": false,
        "creation": "2024-12-25T04:58:11.034Z",
        "lastAccessed": "2024-12-25T04:58:11.034Z"
    },
    {
        "key": "ps_l",
        "value": "1",
        "domain": "facebook.com",
        "path": "/",
        "hostOnly": false,
        "creation": "2024-12-25T04:58:11.034Z",
        "lastAccessed": "2024-12-25T04:58:11.034Z"
    },
    {
        "key": "vpd",
        "value": "v1%3B777x412x2.625",
        "domain": "facebook.com",
        "path": "/",
        "hostOnly": false,
        "creation": "2024-12-25T04:58:11.034Z",
        "lastAccessed": "2024-12-25T04:58:11.034Z"
    },
    {
        "key": "dpr",
        "value": "2.625",
        "domain": "facebook.com",
        "path": "/",
        "hostOnly": false,
        "creation": "2024-12-25T04:58:11.034Z",
        "lastAccessed": "2024-12-25T04:58:11.034Z"
    },
    {
        "key": "wl_cbv",
        "value": "v2%3Bclient_version%3A2692%3Btimestamp%3A1733804757",
        "domain": "facebook.com",
        "path": "/",
        "hostOnly": false,
        "creation": "2024-12-25T04:58:11.034Z",
        "lastAccessed": "2024-12-25T04:58:11.034Z"
    },
    {
        "key": "locale",
        "value": "en_GB",
        "domain": "facebook.com",
        "path": "/",
        "hostOnly": false,
        "creation": "2024-12-25T04:58:11.034Z",
        "lastAccessed": "2024-12-25T04:58:11.034Z"
    },
    {
        "key": "datr",
        "value": "lMJqZ3PbxRJUl35CT7YQ5Xnm",
        "domain": "facebook.com",
        "path": "/",
        "hostOnly": false,
        "creation": "2024-12-25T04:58:11.034Z",
        "lastAccessed": "2024-12-25T04:58:11.034Z"
    },
    {
        "key": "c_user",
        "value": "100039740203430",
        "domain": "facebook.com",
        "path": "/",
        "hostOnly": false,
        "creation": "2024-12-25T04:58:11.034Z",
        "lastAccessed": "2024-12-25T04:58:11.034Z"
    },
    {
        "key": "wd",
        "value": "980x1961",
        "domain": "facebook.com",
        "path": "/",
        "hostOnly": false,
        "creation": "2024-12-25T04:58:11.034Z",
        "lastAccessed": "2024-12-25T04:58:11.034Z"
    },
    {
        "key": "fr",
        "value": "10IEwuv8EyQRFlcoe.AWWkvtWp539ph-ExJigKJhd1HfQ.Bna5DA..AAA.0.0.Bna5DA.AWWeEM2Kddg",
        "domain": "facebook.com",
        "path": "/",
        "hostOnly": false,
        "creation": "2024-12-25T04:58:11.034Z",
        "lastAccessed": "2024-12-25T04:58:11.034Z"
    },
    {
        "key": "xs",
        "value": "42%3AvrDextgb01j2sQ%3A2%3A1735049953%3A-1%3A5903%3A%3AAcXDmE5fFM8t_8KCwNBG8rXIEReYzTk3IhhgLsyfLA",
        "domain": "facebook.com",
        "path": "/",
        "hostOnly": false,
        "creation": "2024-12-25T04:58:11.034Z",
        "lastAccessed": "2024-12-25T04:58:11.034Z"
    },
    {
        "key": "presence",
        "value": "C%7B%22lm3%22%3A%22g.7007817215968702%22%2C%22t3%22%3A%5B%5D%2C%22utc3%22%3A1735102690884%2C%22v%22%3A1%7D",
        "domain": "facebook.com",
        "path": "/",
        "hostOnly": false,
        "creation": "2024-12-25T04:58:11.034Z",
        "lastAccessed": "2024-12-25T04:58:11.034Z"
    }
]
